{
    "start_time": 1521914693000,
    "end_time": 1521915497000,
    "created_at": 1521915504000,
    "updated_at": 1521915505000,
    "start_time_timezone_offset": -14400000,
    "end_time_timezone_offset": -14400000,
    "distance": 2290,
    "duration": 803999,
    "elevation_gain": 14,
    "elevation_loss": 13,
    "average_speed": 10.2528324127197,
    "calories": 173,
    "longitude": -78.927116394043,
    "latitude": 36.0041465759277,
    "max_speed": 15.4405632019043,
    "pause_duration": 1,
    "duration_per_km": 351091,
    "temperature": 10.0,
    "manual": false,
    "edited": false,
    "completed": true,
    "live_tracking_active": false,
    "live_tracking_enabled": false,
    "cheering_enabled": false,
    "indoor": false,
    "id": "fb461b1b-3c60-425d-bd42-7c7b97ed1ec0",
    "weather_condition_id": "2",
    "subjective_feeling_id": "5",
    "sport_type_id": "1"
}